countapi/__init__.py
countapi/common.py
countapi/create.py
countapi/info.py
countapi/set.py
countapi/stats.py
countapi/value.py
countapi-1.0.dist-info/LICENSE
countapi-1.0.dist-info/METADATA
countapi-1.0.dist-info/WHEEL
countapi-1.0.dist-info/top_level.txt
countapi-1.0.dist-info/RECORD
