Metadata-Version: 2.1
Name: countapi
Version: 1.0
Summary: An unofficial Python client library for CountAPI (countapi.xyz).
Home-page: https://github.com/BenJetson/py-countapi
Author: Ben Godfrey
Author-email: BenJetson@users.noreply.github.com
License: UNKNOWN
Platform: UNKNOWN
Classifier: Programming Language :: Python :: 3
Classifier: License :: OSI Approved :: MIT License
Classifier: Operating System :: OS Independent
Requires-Python: >=3.6
